{"generated_on":1640276761025,"data":[{"alpha":"aegino","words":["agonie"]},{"alpha":"aaccinost","words":["accointas"]},{"alpha":"aeiimorrtz","words":["amortiriez"]},{"alpha":"-aikprsse","words":["après-ski"]},{"alpha":"aaimpttu","words":["amputait"]},{"alpha":"-aaeeiinnorrrssse","words":["arrière-saisonnes"]},{"alpha":"aeeilnnooppsssv","words":["enveloppassions"]},{"alpha":"cehiios","words":["choisie"]},{"alpha":"eeeoprsxz","words":["exposerez"]},{"alpha":"aginnorsss","words":["garnissons"]},{"alpha":"cceeimnnopte","words":["incompétence"]},{"alpha":"abceinorrrsu","words":["carburerions"]},{"alpha":"ceinossttu","words":["constitues"]},{"alpha":"aceirstuze","words":["cautérisez"]},{"alpha":"'elqrruee","words":["l'équerré"]},{"alpha":"'eilpque","words":["l'équipe","qu'épile","l'épique"]},{"alpha":"'acelnorre","words":["l'écornera"]},{"alpha":"'aeilllnnorsssstee","words":["l'étrésillonnasses"]},{"alpha":"'aaabdinnorssstu","words":["n'abasourdissant"]},{"alpha":"'aenrsstvi","words":["n'asservît"]},{"alpha":"'aaeiimnopsssstu","words":["m'assoupissaient"]},{"alpha":"aaaiiilmmnostx","words":["maximalisation"]},{"alpha":"efimsee","words":["méfiées"]},{"alpha":"'aceeeillmnorrsttye","words":["m'électrolyseraient"]},{"alpha":"'abcehmnrre","words":["m'ébrancher"]},{"alpha":"'aemnnnoorsstce","words":["m'étronçonnasse"]},{"alpha":"abellnnot","words":["ballonnet"]},{"alpha":"befinquee","words":["bénéfique"]},{"alpha":"eiinooprsste","words":["poétiserions"]},{"alpha":"aceinnnooprrttue","words":["précautionneront"]},{"alpha":"adiimprttee","words":["préméditait"]},{"alpha":"eeefimorrrz","words":["reformeriez"]},{"alpha":"aagilrse","words":["régalais"]},{"alpha":"diinnoorrsstue","words":["réintroduisons"]},{"alpha":"acceilrsy","words":["recyclais","cyclisera"]},{"alpha":"aaceinnorrsti","words":["reconnaîtrais"]},{"alpha":"aaelnrty","words":["relayant"]},{"alpha":"eeeilrsu","words":["relieuse"]},{"alpha":"eeeglmnoprsa","words":["replongeâmes"]},{"alpha":"eeennnprrt","words":["reprennent"]},{"alpha":"eiiqrsuz","words":["risquiez"]},{"alpha":"'aborssue","words":["s'ébrouas"]},{"alpha":"'aaacdehlnst","words":["t'achalandes"]},{"alpha":"'aaaeiiinnsssstt","words":["t'assainissaient"]},{"alpha":"accdeehnorstte","words":["décachetterons"]},{"alpha":"aacdeeillprse","words":["décapellerais"]},{"alpha":"'eeeiiinrrsstttvz","words":["t'intervertissiez"]},{"alpha":"adhiinopsu","words":["dauphinois"]},{"alpha":"aacinostv","words":["vacations"]},{"alpha":"aehilorste","words":["aérolithes"]},{"alpha":"aainoppst","words":["appointas","appontais"]},{"alpha":"beeellmnoorstt","words":["embottellerons"]},{"alpha":"-aaccdeinrrsssstue","words":["assurances-crédits"]},{"alpha":"-abeeejmnrt","words":["entre-jambe"]},{"alpha":"ehlstae","words":["hélâtes"]},{"alpha":"acehnosstu","words":["essouchant"]},{"alpha":"aaefimnstz","words":["fantasmiez"]},{"alpha":"deefistu","words":["feudiste"]},{"alpha":"aaacdeefinrrtu","words":["faucarderaient"]},{"alpha":"aadglnrse","words":["gardénals"]},{"alpha":"aeglorssstu","words":["glossateurs"]},{"alpha":"'aeegjnnossc","words":["j'engonçasse"]},{"alpha":"'adegiijnorru","words":["j'engourdirai"]},{"alpha":"'aaaceiiimnnqrstue","words":["qu'américanisaient"]},{"alpha":"'aaaeiiilmnqsssuz","words":["qu'animalisassiez"]},{"alpha":"'abeqsstuua","words":["qu'abusâtes"]},{"alpha":"'aeiioqrssuuvz","words":["qu'assouviriez"]},{"alpha":"'adeimnoqsttu","words":["qu'admettions"]},{"alpha":"'eeiioqqqruuuvze","words":["qu'équivoqueriez"]},{"alpha":"abceeillostte","words":["caillebottées"]},{"alpha":"'eeiinqruvz","words":["qu'enivriez"]},{"alpha":"'ailmnpqstuu","words":["qu'impulsant"]},{"alpha":"'aeiilmopqssttua","words":["qu'optimalisâtes"]},{"alpha":"aceioorrrs","words":["corroieras"]},{"alpha":"aeelqruz","words":["laquerez"]},{"alpha":"'ceellnnotu","words":["l'enclouent"]},{"alpha":"'aaccdeiilrrste","words":["l'accréditerais"]},{"alpha":"'aeilm","words":["l'amie","l'aime"]},{"alpha":"'aeellmmpsa","words":["l'empalâmes"]},{"alpha":"'aaeilnprste","words":["l'apaisèrent"]},{"alpha":"aelmmorsya","words":["larmoyâmes"]},{"alpha":"'aabeilrrsst","words":["l'arbitrasse"]},{"alpha":"'aclore","words":["l'écora"]},{"alpha":"'celore","words":["l'écore"]},{"alpha":"'aaceeilllmmorssu","words":["l'emmouscailleras"]},{"alpha":"'aeilnnnorssste","words":["l'étrennassions"]},{"alpha":"'eeilnootxx","words":["l'exotoxine"]},{"alpha":"'aciillnnoqsssuu","words":["l'inculquassions"]},{"alpha":"'aaceilmpssst","words":["l'impactasses"]},{"alpha":"'ceelorsu","words":["l'ocreuse"]},{"alpha":"'aaiilopc","words":["l'opiaçai"]},{"alpha":"'hloost","words":["l'hosto"]},{"alpha":"eilntue","words":["luétine","lutéine","lutinée"]},{"alpha":"'ceehinnnorstve","words":["n'enchevêtrions"]},{"alpha":"acehimrssuza","words":["mâchurassiez"]},{"alpha":"'aabeimmsssa","words":["m'abaissâmes"]},{"alpha":"'aabmnorrt","words":["m'arborant"]},{"alpha":"'aaceiinossssz","words":["n'associassiez"]},{"alpha":"'aainntttue","words":["n'atténuait"]},{"alpha":"'aadeegmmmnnot","words":["m'endommageant"]},{"alpha":"'ceehilmnnoze","words":["m'échelonniez"]},{"alpha":"'agntyae","words":["n'égayât"]},{"alpha":"'eglmnnortee","words":["m'élongèrent"]},{"alpha":"'aeeimoprsssttue","words":["m'époussetterais"]},{"alpha":"eegimnrstua","words":["meringuâtes"]},{"alpha":"'ehimnsstae","words":["n'hésitâmes"]},{"alpha":"'aceemnnoorstt","words":["n'escamoteront"]},{"alpha":"'aiiinnsttu","words":["n'instituai"]},{"alpha":"'aiiimmnnstu","words":["n'immunisait"]},{"alpha":"'aehiiilnnoprrt","words":["n'horripilaient"]},{"alpha":"eimnooorrsst","words":["motoriserons"]},{"alpha":"aceiops","words":["opiaces"]},{"alpha":"cnooosty","words":["otocyons"]},{"alpha":"aaeeiiilnoprstt","words":["potentialiserai"]},{"alpha":"deipqrsue","words":["prédiques"]},{"alpha":"eilprtvee","words":["réplétive"]},{"alpha":"deeinorsst","words":["retondisse"]},{"alpha":"'-adeeeegnnrrrstt","words":["s'entre-regardent"]},{"alpha":"'afinsttua","words":["s'infatuât"]},{"alpha":"'aacdhrre","words":["d'arraché"]},{"alpha":"'aaccddeimnnoorse","words":["d'adénocarcinomes"]},{"alpha":"'adeeimrtttz","words":["t'admettriez"]},{"alpha":"'adeghilnoot","words":["d'anthologie"]},{"alpha":"aaiotttu","words":["tatouait"]},{"alpha":"acceehiinorsttz","words":["technocratisiez"]},{"alpha":"aehti","words":["thaïe"]},{"alpha":"'deeggmnorte","words":["d'égorgement"]},{"alpha":"adiilre","words":["délirai"]},{"alpha":"acdeennorrssste","words":["désencrasseront"]},{"alpha":"adeeiillnorsssttze","words":["désentortillassiez"]},{"alpha":"'ceeeimmnortuxz","words":["t'excommunierez"]},{"alpha":"aadeilssst","words":["dilatasses"]},{"alpha":"'abdeillnorte","words":["d'intolérable"]},{"alpha":"'deiiinnsssttu","words":["t'induisissent"]},{"alpha":"adegmopst","words":["domptages"]},{"alpha":"adnopprt","words":["droppant"]},{"alpha":"aeiloprstuuv","words":["voluptuaires"]}]}