{"generated_on":1640276760285,"data":[{"alpha":"aeelnrve","words":["enlèvera"]},{"alpha":"aaefiiilmprs","words":["amplifierais","plasmifierai"]},{"alpha":"acceeelnrss","words":["encerclasse"]},{"alpha":"aeinpqsstue","words":["équipassent"]},{"alpha":"aeeloprtxe","words":["extrapolée"]},{"alpha":"aeeflrttz","words":["flatterez"]},{"alpha":"aacdefinrux","words":["fricandeaux"]},{"alpha":"ceilmnnste","words":["incléments"]},{"alpha":"eiinnnorst","words":["internions"]},{"alpha":"aklo","words":["kola"]},{"alpha":"'eillmnoopsy","words":["l'employions"]},{"alpha":"'abeeiilmnorttu","words":["l'emboutiraient"]},{"alpha":"'ailnoqrstue","words":["l'étarquions","qu'altérions"]},{"alpha":"beilllse","words":["libellés"]},{"alpha":"eiilosstz","words":["lotissiez"]},{"alpha":"befiiilruz","words":["lubrifiiez"]},{"alpha":"'aabeeinnrtuv","words":["n'abreuvaient"]},{"alpha":"'aabenorstu","words":["n'abouteras"]},{"alpha":"'aiimnoosssssuv","words":["m'assouvissions"]},{"alpha":"'aaccehinrte","words":["n'écacherait"]},{"alpha":"'aamnnnortue","words":["n'énamourant"]},{"alpha":"'innpsee","words":["n'épinés"]},{"alpha":"aelmnrs","words":["merlans"]},{"alpha":"'aiimorstte","words":["m'érotisait"]},{"alpha":"'abeimnorsssttu","words":["m'estourbissant"]},{"alpha":"'aeiinqrrtue","words":["n'étriquerai"]},{"alpha":"ellnu","words":["nulle"]},{"alpha":"oprtae","words":["opérât"]},{"alpha":"abeeioorrstv","words":["observatoire"]},{"alpha":"aeeillpte","words":["pailletée"]},{"alpha":"berstu","words":["brutes","rebuts","turbes"]},{"alpha":"aeeeimnprsstt","words":["rapetissement"]},{"alpha":"aeimnnrrtee","words":["réanimèrent","maniérèrent"]},{"alpha":"aeelmoprssye","words":["réemployasse"]},{"alpha":"ceefiirstta","words":["rectifiâtes","certifiâtes"]},{"alpha":"aeerrstu","words":["restaure"]},{"alpha":"ademnorrrse","words":["redémarrons","démarrerons"]},{"alpha":"cehimsss","words":["schismes"]},{"alpha":"'aeeeimnorrsuz","words":["s'enamoureriez"]},{"alpha":"'abhisse","words":["s'ébahis"]},{"alpha":"'aaiinoprsue","words":["s'épanouirai"]},{"alpha":"eeirrsssstu","words":["sertisseurs","sertissures"]},{"alpha":"aeeilssstuxa","words":["sexualisâtes"]},{"alpha":"iinorssuv","words":["suivrions"]},{"alpha":"eirssuvv","words":["survives"]},{"alpha":"-aeeimnosssssttu","words":["sous-estimassent"]},{"alpha":"'aahirrtu","words":["t'ahurira"]},{"alpha":"dejoue","words":["déjoue"]},{"alpha":"'aceilsstuze","words":["t'éculassiez"]},{"alpha":"aeillstta","words":["taillâtes"]},{"alpha":"adilmnosste","words":["démolissant"]},{"alpha":"adeillprsee","words":["dépareillés"]},{"alpha":"adeimorsste","words":["désatomiser"]},{"alpha":"derrttae","words":["déterrât"]},{"alpha":"aaiiilrstttu","words":["titularisait"]},{"alpha":"acdennorrstte","words":["transcodèrent"]},{"alpha":"eprrsuu","words":["usurper"]},{"alpha":"aaffiilors","words":["affriolais"]},{"alpha":"affirttua","words":["affruitât"]},{"alpha":"aceilnorti","words":["encloîtrai"]},{"alpha":"aceeehimprssz","words":["emperchassiez"]},{"alpha":"beeimnorrsve","words":["embrèverions"]},{"alpha":"abeeegiimnnrrtu","words":["embringueraient"]},{"alpha":"ceeinre","words":["encirée"]},{"alpha":"acelnruee","words":["énucléera"]},{"alpha":"aeegiinnrvz","words":["invaginerez"]},{"alpha":"biiiiilnsstve","words":["invisibilités"]},{"alpha":"'aeegjnr","words":["j'enrage"]},{"alpha":"'aeijnorstu","words":["j'entourais"]},{"alpha":"eeejnssuu","words":["jeûneuses"]},{"alpha":"'aeiijnpre","words":["j'épinerai"]},{"alpha":"'aaaeffiinqsstu","words":["qu'affaissaient"]},{"alpha":"'acffhiqrtua","words":["qu'affrichât"]},{"alpha":"'aaceinqrsstu","words":["qu'encastrais","qu'encrassait"]},{"alpha":"'aacceoqssuu","words":["qu'accouasse"]},{"alpha":"'adeeeimnqruz","words":["qu'amenderiez"]},{"alpha":"'aaabdinnnnooqsssu","words":["qu'abandonnassions"]},{"alpha":"'eeegimnpqruz","words":["qu'empreignez"]},{"alpha":"'aegioqrttuue","words":["qu'égoutterai"]},{"alpha":"'eiipqssuze","words":["qu'épissiez"]},{"alpha":"'aeeopqrruvze","words":["qu'évaporerez"]},{"alpha":"'acdeeiinnqssu","words":["qu'incendiasse"]},{"alpha":"aceeeiinnqssssstu","words":["quintessenciasses"]},{"alpha":"ccelnosssu","words":["conclusses"]},{"alpha":"aacemnopsssst","words":["compassassent"]},{"alpha":"bceenoorsttue","words":["contreboutées"]},{"alpha":"'dlnoqtuua","words":["qu'ondulât"]},{"alpha":"'abennoqttu","words":["qu'obtenant"]},{"alpha":"aacceehrrvz","words":["cravacherez"]},{"alpha":"aciiilmnrse","words":["criminalisé"]},{"alpha":"'eeglnorssz","words":["l'engrossez"]},{"alpha":"aelnqrtue","words":["laquèrent"]},{"alpha":"'aaaciilllns","words":["l'alcalinisa"]},{"alpha":"'aalopsst","words":["l'apostas"]},{"alpha":"'aadiilmnrst","words":["l'administra"]},{"alpha":"'aeilnnnot","words":["l'entonnai"]},{"alpha":"'aceeilnnooprssstu","words":["l'entrecoupassions"]},{"alpha":"'aeiilnossv","words":["l'avoisines"]},{"alpha":"'aeilnnsuy","words":["l'ennuyais"]},{"alpha":"'aeeeelrrrrstttx","words":["l'extraterrestre"]},{"alpha":"'-aaggiilllnn","words":["l'ilang-ilang"]},{"alpha":"'adegiiilnnrs","words":["l'indignerais"]},{"alpha":"'aaaggmnrtv","words":["m'aggravant"]},{"alpha":"'aaceegnnnt","words":["n'encageant"]},{"alpha":"'ceeeillmnorz","words":["m'encolleriez"]},{"alpha":"'aaelnnrsy","words":["n'analyser"]},{"alpha":"'adennnopprrs","words":["n'apprendrons"]},{"alpha":"'aabbeimorrst","words":["m'absorberait"]},{"alpha":"'aeimmnrrt","words":["m'arriment"]},{"alpha":"'aeennstttta","words":["n'attentâtes"]},{"alpha":"'aabdeeinnru","words":["n'endauberai"]},{"alpha":"'acehlnnnnote","words":["n'échelonnant"]},{"alpha":"'acdimnnostue","words":["m'éconduisant"]},{"alpha":"'acimortce","words":["m'écorçait"]},{"alpha":"'aeelmssve","words":["m'élevasse"]},{"alpha":"'acdeinrte","words":["n'édictera"]},{"alpha":"'aeeimnoprrsst","words":["m'interposeras"]},{"alpha":"'ehimnnnrtue","words":["n'inhumèrent"]},{"alpha":"'aehhnopqrtuye","words":["n'hypothéquera"]},{"alpha":"aimnnot","words":["mitonna"]},{"alpha":"aaegiinnorsssz","words":["organsinassiez"]},{"alpha":"aaelnprrte","words":["parentéral"]},{"alpha":"--bdeeeillntu","words":["belle-de-nuit"]},{"alpha":"iippt","words":["pipit"]},{"alpha":"abceiilnpssstte","words":["plébiscitassent"]},{"alpha":"abnosstu","words":["bossuant"]},{"alpha":"aceimopprrte","words":["précompterai"]},{"alpha":"alprsu","words":["pulsar"]},{"alpha":"aainrs","words":["rainas"]},{"alpha":"'aemnrssstue","words":["s'assumèrent"]},{"alpha":"aennnorst","words":["santonner","tannerons"]},{"alpha":"aceeilnnosssste","words":["sélectionnasses"]},{"alpha":"'aeeinoprrsttx","words":["s'expatrieront","t'expatrierons"]},{"alpha":"'aeinooppsst","words":["s'opposaient"]},{"alpha":"abeirsssu","words":["surbaisse"]},{"alpha":"'ceelnostu","words":["t'encloues"]},{"alpha":"'adeegmmnnott","words":["t'endommagent"]},{"alpha":"aadfillorsue","words":["défouraillas"]},{"alpha":"aacdeehnnrsste","words":["désenchanteras"]},{"alpha":"'aaceeglnorsstv","words":["t'esclavagerons"]},{"alpha":"'abceeenrrttxe","words":["t'exacerbèrent"]},{"alpha":"'eegprtuxz","words":["t'expurgez"]},{"alpha":"aeiqssstu","words":["tiquasses"]},{"alpha":"'deillrstue","words":["d'illustrée"]},{"alpha":"'adeeimmnnst","words":["d'immanentes"]},{"alpha":"'abcdeeiillnpx","words":["d'inexplicable"]},{"alpha":"'aeefilnnssstuc","words":["t'influençasses"]},{"alpha":"'addeeinnntt","words":["d'intendante"]},{"alpha":"'iimnoopprst","words":["t'opprimions"]},{"alpha":"-abccehhinoorrstte","words":["trachéo-bronchites"]}]}