{"generated_on":1640276760451,"data":[{"alpha":"aacehmnrsa","words":["acharnâmes"]},{"alpha":"aejrstu","words":["ajuster","rajuste","juteras","surjeta"]},{"alpha":"aeorst","words":["aortes"]},{"alpha":"aadfinoopprrs","words":["approfondiras"]},{"alpha":"eiinssuv","words":["ensuivis"]},{"alpha":"arsssue","words":["assurés"]},{"alpha":"aeeinnrtt","words":["entraient","intentera","trentaine","rentaient"]},{"alpha":"ltue","words":["élut","luté"]},{"alpha":"eeimmrssae","words":["émerisâmes"]},{"alpha":"aeinopsssue","words":["épanouisses"]},{"alpha":"aceeorrst","words":["escortera"]},{"alpha":"eeimnstt","words":["estiment","minettes"]},{"alpha":"aefiillmnortu","words":["fourmillaient"]},{"alpha":"eegrsve","words":["grevées","vergées"]},{"alpha":"eiimmnoprrs","words":["imprimerons"]},{"alpha":"eeiimoprrsvz","words":["improviserez"]},{"alpha":"aeginostt","words":["gestation","attigeons"]},{"alpha":"eqstuee","words":["quêtées"]},{"alpha":"abcellnoorrte","words":["collaborèrent"]},{"alpha":"cgillose","words":["colligés"]},{"alpha":"aceimnopss","words":["compensais"]},{"alpha":"ceilmnnorsu","words":["culminerons"]},{"alpha":"'aegillnosssuue","words":["l'égueulassions"]},{"alpha":"'aaemnnnstei","words":["n'anéantîmes"]},{"alpha":"'aeeffiilnrrtu","words":["n'effleurirait"]},{"alpha":"aemnnosstt","words":["montassent"]},{"alpha":"ehnoorr","words":["honorer"]},{"alpha":"acehnp","words":["pencha"]},{"alpha":"aaaehipprr","words":["parapherai"]},{"alpha":"eeeimnnprttvve","words":["préventivement"]},{"alpha":"abiirss","words":["brisais"]},{"alpha":"allmrtua","words":["rallumât"]},{"alpha":"aaddeffiinorssstu","words":["radiodiffusassent"]},{"alpha":"ailrssee","words":["réalisés"]},{"alpha":"aeegilrrse","words":["regèlerais"]},{"alpha":"adeeffirssssu","words":["rediffusasses"]},{"alpha":"aaeiilnoorrsstv","words":["revalorisations"]},{"alpha":"eeenorrrstv","words":["reverseront"]},{"alpha":"eersstt","words":["setters"]},{"alpha":"efgiiinnrste","words":["signifièrent"]},{"alpha":"eistuz","words":["situez"]},{"alpha":"aellmorssu","words":["slalomeurs"]},{"alpha":"adeiilors","words":["solidaire","iodlerais"]},{"alpha":"delmossa","words":["soldâmes"]},{"alpha":"aadefirre","words":["défraiera"]},{"alpha":"adefgrze","words":["dégrafez"]},{"alpha":"dgreee","words":["dégréé"]},{"alpha":"aacdilmntae","words":["décalaminât"]},{"alpha":"delopyee","words":["déployée"]},{"alpha":"adhiirstee","words":["déshéritai"]},{"alpha":"acdehtze","words":["détachez"]},{"alpha":"'eenrttvee","words":["t'éventrée"]},{"alpha":"aillorstt","words":["tortillas"]},{"alpha":"acenorrtt","words":["traceront"]},{"alpha":"aeegimnssstv","words":["vagissements"]},{"alpha":"aeginttvee","words":["végétaient"]},{"alpha":"eeirsstuv","words":["vitreuses"]},{"alpha":"aeilnstae","words":["aliénâtes"]},{"alpha":"aeeiilmnnrsu","words":["enluminerais"]},{"alpha":"aeinrrssue","words":["arséniures"]},{"alpha":"adeillnoru","words":["andouiller"]},{"alpha":"abehmrssei","words":["hébraïsmes"]},{"alpha":"aeeiissstvz","words":["estivassiez"]},{"alpha":"afinoqrsu","words":["forniquas"]},{"alpha":"aaegirssstv","words":["gravitasses"]},{"alpha":"eeglmmnorrte","words":["grommelèrent"]},{"alpha":"aceeghioruz","words":["gouacheriez"]},{"alpha":"'aaeijnoprtuve","words":["j'épouvanterai"]},{"alpha":"'aaeffinqsstu","words":["qu'affaissent"]},{"alpha":"'accdemmmooqsua","words":["qu'accommodâmes"]},{"alpha":"'aceeinpqrssuze","words":["qu'encrêpassiez"]},{"alpha":"'abeeiillmnoqrtuu","words":["qu'embrouillaient"]},{"alpha":"'aeiimnoopqrsssssuue","words":["qu'empoussiérassions"]},{"alpha":"acersstta","words":["castrâtes"]},{"alpha":"aaacehlrrt","words":["catarrhale"]},{"alpha":"'aadeeiinnqrtttu","words":["qu'atteindraient"]},{"alpha":"'aaenqrsstuve","words":["qu'avérassent"]},{"alpha":"'aaeiinqrtuv","words":["qu'avinerait"]},{"alpha":"'acdehquue","words":["qu'échaude"]},{"alpha":"'aeeginopqrsssuux","words":["qu'expurgeassions"]},{"alpha":"'cemoqrsua","words":["qu'ocrâmes"]},{"alpha":"'begiloqu","words":["qu'oblige"]},{"alpha":"'aelnoqrtuue","words":["qu'auréolent"]},{"alpha":"'aeeglnnrtve","words":["l'engavèrent"]},{"alpha":"'accdlmmnooos","words":["l'accommodons"]},{"alpha":"'aeilnrtt","words":["l'entrait"]},{"alpha":"'adglre","words":["l'égard"]},{"alpha":"'aaceeilllmmorsu","words":["l'emmouscaillera"]},{"alpha":"'aellnoprte","words":["l'épaleront"]},{"alpha":"'beehlnrt","words":["l'herbent"]},{"alpha":"'aceiilmnnrtte","words":["l'incrémentait"]},{"alpha":"'eeiiilnprrsz","words":["l'inspireriez"]},{"alpha":"'egiilmnsstua","words":["l'instiguâmes"]},{"alpha":"'abeegiillossz","words":["l'obligeassiez"]},{"alpha":"'adiloxy","words":["l'oxydai"]},{"alpha":"'aceeiimrtvz","words":["m'activeriez"]},{"alpha":"'aacceeilmnnrtuu","words":["n'accumuleraient"]},{"alpha":"'aaeeinnnrtx","words":["n'annexerait"]},{"alpha":"'aaennrsttue","words":["n'atténueras"]},{"alpha":"'adinnoosss","words":["n'adossions"]},{"alpha":"'aeeeinnorssttvzu","words":["n'entrevoûtassiez"]},{"alpha":"'cdeiinnosuze","words":["n'éconduisiez"]},{"alpha":"'acehmnnsstee","words":["n'éméchassent"]},{"alpha":"'aiimmnnootte","words":["m'émotionnait"]},{"alpha":"'aemmnru","words":["n'emmura"]},{"alpha":"'abhnnttee","words":["n'hébétant"]},{"alpha":"acdeimorty","words":["myocardite"]},{"alpha":"'aaegiimmnsss","words":["m'imaginasses"]},{"alpha":"'aefiimnnnort","words":["n'informaient"]},{"alpha":"'abeiiimnqrssuz","words":["n'imbriquassiez"]},{"alpha":"'eiinnnoorsssta","words":["n'insonorisâtes"]},{"alpha":"'abbeiilnnossuz","words":["n'obnubilassiez"]},{"alpha":"'ennooopprss","words":["n'opposerons"]},{"alpha":"'afhiimnorrt","words":["m'horrifiant"]},{"alpha":"'aeinnrrsu","words":["n'urineras"]},{"alpha":"'aelnorru","words":["n'ourlera"]},{"alpha":"aaceiosstv","words":["octaviasse"]},{"alpha":"beegmnortu","words":["bougrement","rembougent"]},{"alpha":"aceeiiprtze","words":["rapiécetiez"]},{"alpha":"eimoqstuyz","words":["zymotiques"]},{"alpha":"'aaffiilnoorssst","words":["t'affriolassions"]},{"alpha":"'acdeltu","words":["d'actuel"]},{"alpha":"'aaeeillnpprrtte","words":["t'appareillèrent"]},{"alpha":"aabesste","words":["tabassée"]},{"alpha":"'abdeehimoprty","words":["d'embryopathie"]},{"alpha":"aabceeiorrsttz","words":["tarabiscoterez"]},{"alpha":"'bdeenorr","words":["d'enrober"]},{"alpha":"'aeiosstyz","words":["t'assoyiez"]},{"alpha":"'deeenoprrst","words":["d'entreposer"]},{"alpha":"'acdeeiilnoqrtuv","words":["d'intervocalique"]},{"alpha":"'accdeeillnnoos","words":["d'occasionnelle"]},{"alpha":"aiinnoorsssttu","words":["tonitruassions"]},{"alpha":"'adeeiilnorstt","words":["d'orientaliste"]},{"alpha":"agiopruuxy","words":["uropygiaux"]},{"alpha":"aegimrsstvee","words":["végétarismes"]},{"alpha":"aeinnnoorrsv","words":["vaironnerons"]}]}