{"generated_on":1640276749172,"data":[{"alpha":"aacdeeeehimnrrsss","words":["adresseermachines"]},{"alpha":"adeeefgnors","words":["afgesnoerde"]},{"alpha":"affiltu","words":["affluit"]},{"alpha":"cdeiinrstt","words":["indirectst","districten"]},{"alpha":"abcdeeeeiimmnnnoorrsst","words":["ondernemerscombinaties"]},{"alpha":"aaaeegillnrv","words":["aanvalligere"]},{"alpha":"aaddegintu","words":["uitdaagden"]},{"alpha":"deenorrstuuv","words":["overstuurden"]},{"alpha":"bcehhiiiiinossttx","words":["exhibitionistisch"]},{"alpha":"bddefgiijknrsu","words":["bedrijfskundig"]},{"alpha":"acehnrs","words":["crashen","ranches","scharen"]},{"alpha":"deeeeegillnnrv","words":["deelleveringen","genivelleerden"]},{"alpha":"dddeeeeiknnp","words":["diepdenkende"]},{"alpha":"ddemoooorrst","words":["doorstroomde"]},{"alpha":"acdeeeeffgrt","words":["geaffecteerd"]},{"alpha":"adeginnrte","words":["gradiënten"]},{"alpha":"cdeeegghiijnnnorrrssv","words":["grensoverschrijdingen"]},{"alpha":"deho","words":["hoed"]},{"alpha":"ehisstuv","words":["huisvest"]},{"alpha":"aagkmmnoprrstu","words":["kunstprogramma"]},{"alpha":"eeekklrr","words":["kerkleer"]},{"alpha":"eekkkmnorrt","words":["kromtrekken"]},{"alpha":"bdlmoooo","words":["loodboom"]},{"alpha":"eegllss","words":["legsels"]},{"alpha":"aaddeggiiijklnnnnos","words":["lijdensaankondiging"]},{"alpha":"aceeghilrt","words":["leerachtig"]},{"alpha":"eiikmmmstu","words":["mummiekist"]},{"alpha":"aeimnsssw","words":["miswassen"]},{"alpha":"aeiklmruz","words":["muzikaler"]},{"alpha":"anrtuu","words":["natuur"]},{"alpha":"eeklnpstu","words":["plusteken"]},{"alpha":"aeeilnnprt","words":["platineren"]},{"alpha":"aeelnoptttv","words":["platvoetten"]},{"alpha":"eegnprru","words":["purgeren"]},{"alpha":"acdehikmnopsyy","words":["psychodynamiek"]},{"alpha":"abeegiinrrsstt","words":["sierbestrating"]},{"alpha":"efflost","words":["stoffel","toffels"]},{"alpha":"bikknost","words":["stinkbok"]},{"alpha":"deeijnnssttu","words":["tussentijden"]},{"alpha":"aadeeijklmnoooorrvw","words":["voornaamwoordelijke"]},{"alpha":"eekoorrrvw","words":["voorwerker"]}]}