{"generated_on":1640276749732,"data":[{"alpha":"achmoops","words":["oomschap"]},{"alpha":"deeehiijklmnot","words":["onmetelijkheid"]},{"alpha":"ddeeilnnps","words":["inspeldden"]},{"alpha":"aaeemmnnwz","words":["aanzwemmen"]},{"alpha":"beiijtttu","words":["uitbijtte"]},{"alpha":"deeghioostu","words":["uitgehoosde"]},{"alpha":"aaaegiknnssstu","words":["uitgaanskassen"]},{"alpha":"beghiinuz","words":["behuizing"]},{"alpha":"abeillnor","words":["ballerino"]},{"alpha":"abeennorrtw","words":["bronwateren"]},{"alpha":"abeeghlnorrst","words":["borstelhanger"]},{"alpha":"bceeehnoorrtv","words":["bevoorrechten"]},{"alpha":"abcchiimnoorst","words":["combinatorisch"]},{"alpha":"abddeelmno","words":["dadelbomen","modebladen"]},{"alpha":"aadlt","words":["daalt","laadt"]},{"alpha":"deempr","words":["demper"]},{"alpha":"cdegoooprrs","words":["droogproces"]},{"alpha":"dikooprru","words":["doorkruip"]},{"alpha":"deekoorw","words":["doorweek"]},{"alpha":"afistuv","words":["fauvist"]},{"alpha":"abdegl","words":["gebald"]},{"alpha":"aeggst","words":["gegast"]},{"alpha":"bceegghiiijknnnooorrstv","words":["grootboekinschrijvingen"]},{"alpha":"adefhijkklooz","words":["hoofdzakelijk"]},{"alpha":"deehlrst","words":["helderst","hersteld"]},{"alpha":"deeeeghlmnrstt","words":["hemeltergendst"]},{"alpha":"aehmn","words":["hamen"]},{"alpha":"aahn","words":["haan"]},{"alpha":"dhhiosuu","words":["huishoud"]},{"alpha":"deeegiiklmno","words":["kleinmoedige"]},{"alpha":"eeeklnooorrssttv","words":["kloosteroversten"]},{"alpha":"aceeghiklnrstv","words":["levenskrachtig"]},{"alpha":"deeikllmst","words":["melkdistel"]},{"alpha":"aiillmoprtu","words":["multipolair"]},{"alpha":"eeiijklnppp","words":["pippelinkje"]},{"alpha":"egnnor","words":["rongen"]},{"alpha":"aceghlrs","words":["schlager"]},{"alpha":"cdeehhipssu","words":["scheepshuid"]},{"alpha":"aabcehnrsu","words":["scheurbaan"]},{"alpha":"aeeimnsz","words":["siamezen","zeiseman"]},{"alpha":"aaaamnrstt","words":["straatnaam"]},{"alpha":"eeenorrsttv","words":["verroestten"]},{"alpha":"deorrvw","words":["verword"]},{"alpha":"abeijlnstvv","words":["vastblijven"]},{"alpha":"abeeeghlnw","words":["welbehagen"]},{"alpha":"bdemnooorw","words":["wonderboom"]},{"alpha":"deeeikllnrsww","words":["wereldwinkels"]}]}