{"generated_on":1640276743413,"data":[{"alpha":"aabcdeennoruv","words":["overabundance"]},{"alpha":"eeorrtuv","words":["overture"]},{"alpha":"elotx","words":["extol"]},{"alpha":"'belrssu","words":["elbrus's"]},{"alpha":"ceilnootu","words":["elocution"]},{"alpha":"aeiiilnrsttt","words":["interstitial"]},{"alpha":"addehstu","words":["thaddeus"]},{"alpha":"beioostz","words":["booziest"]},{"alpha":"'aefimrrsw","words":["firmware's"]},{"alpha":"ahhmprru","words":["harrumph"]},{"alpha":"'efglors","words":["golfer's"]},{"alpha":"cefnostu","words":["confutes"]},{"alpha":"'cginorstuy","words":["congruity's"]},{"alpha":"'jorrsu","words":["juror's"]},{"alpha":"'ijrsstu","words":["jurist's"]},{"alpha":"ciimms","words":["mimics"]},{"alpha":"'aeklmorstw","words":["metalwork's"]},{"alpha":"ghilnty","words":["nightly"]},{"alpha":"ceeefprrt","words":["perfecter"]},{"alpha":"eiipx","words":["pixie"]},{"alpha":"appu","words":["pupa"]},{"alpha":"ceelrssu","words":["recluses"]},{"alpha":"cdeehlrtwy","words":["wretchedly"]},{"alpha":"aaccfiiilrs","words":["sacrificial"]},{"alpha":"eiloppsst","words":["sloppiest"]},{"alpha":"'aeegikllnpssw","words":["sleepwalking's"]},{"alpha":"aabcdeennprsuu","words":["superabundance"]},{"alpha":"ceehoopsstt","words":["stethoscope"]},{"alpha":"adeisstt","words":["staidest","distaste"]},{"alpha":"aaellssw","words":["seawalls"]},{"alpha":"deelorttuv","words":["turtledove"]},{"alpha":"fkloorsww","words":["workflows"]},{"alpha":"iiklnnosw","words":["wilkinson"]},{"alpha":"aeegiillnv","words":["villeinage"]},{"alpha":"'eillnoosssw","words":["woolliness's"]},{"alpha":"deellovy","words":["volleyed"]},{"alpha":"'addeensswy","words":["wednesday's"]}]}