{"generated_on":1640276743500,"data":[{"alpha":"'aaefhqrssu","words":["aquafresh's"]},{"alpha":"ceelsx","words":["excels"]},{"alpha":"aacfiiilmnopst","words":["amplifications"]},{"alpha":"aceeiinnrt","words":["incinerate"]},{"alpha":"aceennrssuy","words":["unnecessary"]},{"alpha":"abelnrttuuy","words":["unutterably"]},{"alpha":"aeeinrsttt","words":["interstate"]},{"alpha":"'abeilmoostu","words":["automobile's"]},{"alpha":"'abeenqrstu","words":["banqueter's"]},{"alpha":"abnrwy","words":["brawny"]},{"alpha":"addeefhlmory","words":["formaldehyde"]},{"alpha":"ehllru","words":["huller"]},{"alpha":"'dehiillss","words":["hillside's"]},{"alpha":"'affgsuw","words":["guffaw's"]},{"alpha":"acelllorss","words":["collarless"]},{"alpha":"aaceilmnstu","words":["calumniates"]},{"alpha":"dggiklnu","words":["kludging"]},{"alpha":"'acdgmnoprsu","words":["campground's"]},{"alpha":"'aaceinrss","words":["canaries's"]},{"alpha":"abcelnorsttu","words":["counterblast"]},{"alpha":"agps","words":["gaps","gasp"]},{"alpha":"'ejsw","words":["jew's"]},{"alpha":"eimrrtt","words":["merritt"]},{"alpha":"einv","words":["nevi","vein","vine"]},{"alpha":"'deinnoost","words":["noontide's"]},{"alpha":"'oprsxy","words":["proxy's"]},{"alpha":"aeknprrst","words":["prankster"]},{"alpha":"aacdeggilop","words":["pedagogical"]},{"alpha":"denoprss","words":["responds"]},{"alpha":"adefrrt","words":["redraft","drafter"]},{"alpha":"aabgginost","words":["sabotaging"]},{"alpha":"'cghilloorss","words":["schoolgirl's"]},{"alpha":"deirssu","words":["sudsier"]},{"alpha":"'cghiinsstt","words":["stitching's"]},{"alpha":"'imrst","words":["trim's"]},{"alpha":"aiorrtt","words":["traitor"]},{"alpha":"adeelosst","words":["desolates"]},{"alpha":"deginoopprst","words":["doorstepping"]},{"alpha":"'aemnrsstvy","words":["vestryman's"]},{"alpha":"'accehinnsss","words":["chanciness's"]}]}