{"generated_on":1640276785937,"data":[{"alpha":"abcddeeeoors","words":["obedecedoras"]},{"alpha":"aabdnsu","words":["abundas","sudaban","sudaban"]},{"alpha":"abeeenrsst","words":["abstenerse","abstenerse"]},{"alpha":"aabeejnrsst","words":["abstrajesen"]},{"alpha":"aaabcre","words":["acabaré","acabaré"]},{"alpha":"aaachnst","words":["achantas"]},{"alpha":"aaachiiiqrstui","words":["achiquitaríais","achiquitaríais"]},{"alpha":"aacelnsto","words":["acótenlas"]},{"alpha":"accinoost","words":["occitanos","occitanos","concitaos","concitaos"]},{"alpha":"aaaaddlpst","words":["adaptadlas","adaptadlas"]},{"alpha":"aaacfiinru","words":["afiuciaran"]},{"alpha":"aeeflmoprsa","words":["afelpáremos","afelpáremos","felpeáramos","felpeáramos"]},{"alpha":"aaabcfiins","words":["afincabais","afincabais"]},{"alpha":"ceeflmoorre","words":["ofrecérmelo"]},{"alpha":"aaegiiilsstz","words":["agilizasteis","agilizasteis"]},{"alpha":"acdeegilmnoa","words":["agenciádmelo"]},{"alpha":"aaacellmnose","words":["almacénaselo","almacénaselo"]},{"alpha":"adilmnoe","words":["almidoné"]},{"alpha":"aabelmmos","words":["embalamos","embalamos","embalsamo"]},{"alpha":"aabeiimnrste","words":["ambientaréis"]},{"alpha":"abejlmorrsu","words":["embrujarlos"]},{"alpha":"aacehmra","words":["amechará","amechará","macheará","macheará"]},{"alpha":"aaegimst","words":["amigaste","amigaste","gamitase","gamitase","miagaste","miagaste"]},{"alpha":"aaaemnn","words":["amanean","mañanea"]},{"alpha":"deeiimprs","words":["impedirse","epidermis"]},{"alpha":"eilmnopqsui","words":["implíquenos"]},{"alpha":"aeeimmps","words":["empiemas"]},{"alpha":"adeeiiimnprs","words":["impendierais"]},{"alpha":"aceiimooprrt","words":["imprecatorio"]},{"alpha":"adeelmnooprsa","words":["empeorándolas","separándomelo"]},{"alpha":"eemoprr","words":["emperro"]},{"alpha":"aaaceeiiimnrrsz","words":["americanizareis","americanizareis"]},{"alpha":"aaacmorrsi","words":["amorcarías","arcaríamos","arcaríamos"]},{"alpha":"elmooti","words":["omítelo"]},{"alpha":"adiilmnooste","words":["omitiéndolas"]},{"alpha":"cehilmnoopssse","words":["enchispémoslos"]},{"alpha":"aacdiimnoors","words":["incomodarais"]},{"alpha":"accddeeelnnos","words":["encandecedlos","encandecedlos"]},{"alpha":"aacenpre","words":["encaparé","encaparé","apencaré","apencaré"]},{"alpha":"aceeinrrs","words":["encierras","encierras","enriscare","enriscare","cernieras","cernieras","recriasen","sincerare","sincerare"]},{"alpha":"aaaceennprrti","words":["encarpetarían"]},{"alpha":"aacdeelnnorttua","words":["encaratulándote"]},{"alpha":"addlnoou","words":["ondulado"]},{"alpha":"adeeinsst","words":["enditases","enditases","dentaseis","desatines","destinase","destinase","sedientas"]},{"alpha":"aacdfiinu","words":["unificada"]},{"alpha":"bdegllnnoooossa","words":["englobándooslos"]},{"alpha":"eeegillmnntuo","words":["enguillótenme"]},{"alpha":"aaaaabegnrrti","words":["engarabataría","engarabataría","garabatearían","garabatearían"]},{"alpha":"aaeegnrst","words":["engastare","engastare","engatares","engatares","engatares","engatares","argentase","arengaste","graneaste","graneaste","gestearan","gestearan","sargentea"]},{"alpha":"aejnoos","words":["enojaos","enojaos","enojosa"]},{"alpha":"aceeeeglmnrrs","words":["enmagrecerles","enmagrecerles"]},{"alpha":"eeelmmnnorsue","words":["enumérenmelos"]},{"alpha":"aabeellnorr","words":["enarbolarle"]},{"alpha":"aeeelnnrsv","words":["enselvaren","enselvaren"]},{"alpha":"ddeeelnnost","words":["entendedlos","entendedlos","desentolden"]},{"alpha":"aeeginrsve","words":["envegaréis"]},{"alpha":"aemoprssua","words":["apurásemos","apurásemos","pausáremos","pausáremos"]},{"alpha":"aaaelllopsstti","words":["apostíllatelas","apostíllatelas"]},{"alpha":"aaccdefhiorr","words":["archicofrade"]},{"alpha":"aaaacdilrsz","words":["arcaizadlas","arcaizadlas","sacralizada"]},{"alpha":"aegiirrr","words":["irrigare","irrigare"]},{"alpha":"aeers","words":["erase","erase"]},{"alpha":"adeginnoorrssa","words":["arriesgándonos"]},{"alpha":"abceillnrsua","words":["escabullirán"]},{"alpha":"ceeelopss","words":["escoplees"]},{"alpha":"aaceeeiiilpsssz","words":["especializaseis","especializaseis"]},{"alpha":"aaaeeiloprssin","words":["españolearíais","españolearíais"]},{"alpha":"aaeprstui","words":["esputaría","esputaría","putearías","putearías"]},{"alpha":"acdeeiilnoqstua","words":["esquiciándotela"]},{"alpha":"aadeglmnooossta","words":["estomagándoosla"]},{"alpha":"aeeellnnnosstta","words":["estantálennosle"]},{"alpha":"aadejorrstu","words":["estrujadora"]},{"alpha":"aeeeiillrrssttza","words":["esterilizártelas"]},{"alpha":"aaeeirssttu","words":["estatuareis"]},{"alpha":"aaabilmorrstui","words":["atribularíamos","atribularíamos"]},{"alpha":"eiiimrsxe","words":["eximiréis"]},{"alpha":"aegilortxa","words":["extráigalo"]},{"alpha":"aadeilnorstvxa","words":["extraviándolas","extraviádnosla"]},{"alpha":"aacccisua","words":["caucásica"]},{"alpha":"acceehimnossa","words":["chicaneásemos","chicaneásemos"]},{"alpha":"acefiillmoqsuue","words":["cualifiquémosle"]},{"alpha":"acdiillmnootza","words":["climatizándolo"]},{"alpha":"acellnrso","words":["clórenlas"]},{"alpha":"aaabcimri","words":["cambiaría"]},{"alpha":"aabcmmopsa","words":["campábamos","campábamos"]},{"alpha":"accddelnnoose","words":["concedédnosla"]},{"alpha":"aaccefilnnostui","words":["cuantifícanosle"]},{"alpha":"acenooprt","words":["contrapeo","cooptaren","cooptaren"]},{"alpha":"aaaceeellmrr","words":["caramelearle"]},{"alpha":"acdeinrru","words":["cernidura"]},{"alpha":"ceelse","words":["césele"]},{"alpha":"aacdeefiilnrrs","words":["diferenciarlas"]},{"alpha":"adddenoo","words":["denodado"]},{"alpha":"aadnnori","words":["donarían"]},{"alpha":"aacddegloss","words":["descolgadas"]},{"alpha":"aacdefinorss","words":["desconfiaras","desconfiaras","fascinadores","fascinadores"]},{"alpha":"cddeeissua","words":["deseducáis","deseducáis"]},{"alpha":"aaddehijlnossa","words":["desahijándolas"]},{"alpha":"adejnos","words":["desojan"]},{"alpha":"aaaadeglnrs","words":["desalagaran","desalagaran"]},{"alpha":"demosi","words":["deísmo","medíos"]},{"alpha":"abcddeeeeimnorssve","words":["desembraveciéndose"]},{"alpha":"adeellmmoopsssve","words":["desempolvémoslas"]},{"alpha":"adeeellmoppsse","words":["desempapélelos"]},{"alpha":"aadeemprsv","words":["desemparva"]},{"alpha":"acdddeeelnnnoosa","words":["desencadenándolo"]},{"alpha":"acddeegilnnooossse","words":["desencogiéndooslas"]},{"alpha":"aaacdeeiilnnosstz","words":["desnacionalizaste","desnacionalizaste"]},{"alpha":"acdeeinnrssta","words":["desencintarás","desencintarás","desinsectarán","desinsectarán"]},{"alpha":"cdeeeeilnnrrse","words":["desenciérrenle"]},{"alpha":"aabdeeelnnnoss","words":["desenlabonasen"]},{"alpha":"ddeilnnooosssan","words":["diseñándonoslos"]},{"alpha":"aacdeehllpssu","words":["despelúchalas","despelúchalas","despelúchalas"]},{"alpha":"aacdehlnprs","words":["desplanchar"]},{"alpha":"adeempsssu","words":["despumases","despumases"]},{"alpha":"adeeeiprssn","words":["despeñareis","despeñareis"]},{"alpha":"dddeeeinnoprste","words":["desprendiéndote"]},{"alpha":"aadeiinoprrstvz","words":["desprivatizaron","desprivatizaron"]},{"alpha":"adeeeiipssstz","words":["despiezasteis"]},{"alpha":"addeenoosssa","words":["desaseándoos"]},{"alpha":"dddeiilnnooste","words":["distendiéndolo"]},{"alpha":"addeioprrst","words":["destripador"]},{"alpha":"aaaderrsvi","words":["desvararía","desvararía"]},{"alpha":"aadiinrsv","words":["divisaran","divisaran"]},{"alpha":"acefhlnsi","words":["fíchenlas"]},{"alpha":"acdflnnoostua","words":["facultándonos"]},{"alpha":"efglnooorsua","words":["fogueárnoslo"]},{"alpha":"aaeflllrssa","words":["fallárselas"]},{"alpha":"aabdfnnu","words":["fundaban"]},{"alpha":"efjno","words":["fonje"]},{"alpha":"aeefglmmnnoorste","words":["fragmentémonosle"]},{"alpha":"aafrrstui","words":["frutarías","frutarías","trufarías","trufarías"]},{"alpha":"finosuo","words":["fusionó"]},{"alpha":"aafnorsi","words":["fosarían"]},{"alpha":"aefmnoosst","words":["festonamos"]},{"alpha":"accefgiiilnoors","words":["glorificaciones"]},{"alpha":"aeeginsstt","words":["genetistas"]},{"alpha":"aadegimnorsz","words":["germanizados"]},{"alpha":"aaadgllrstu","words":["gratuladlas","gratuladlas"]},{"alpha":"adeegilmnossta","words":["gestionádmelas"]},{"alpha":"eehijlmosu","words":["hijuelemos"]},{"alpha":"aehijlnu","words":["hijuelan"]},{"alpha":"aceghiilmopsu","words":["hipoglucemias"]},{"alpha":"aeghimnoors","words":["hormigonase"]},{"alpha":"aehmpse","words":["héspame"]},{"alpha":"aellmmnoosa","words":["lamámonosle"]},{"alpha":"aeillssi","words":["lísielas","lísiales","lísiales"]},{"alpha":"eillmnooz","words":["mollizneo"]},{"alpha":"aceeiimmnnostu","words":["minuciosamente"]},{"alpha":"aaacdflmnorstuu","words":["manufacturadlos","manufacturadlos"]},{"alpha":"diiilmmnnooza","words":["minimizándolo"]},{"alpha":"aammnoorsti","words":["montaríamos"]},{"alpha":"adegilmnnorsa","words":["marginándoles"]},{"alpha":"ailmoott","words":["motolita"]},{"alpha":"aabceimnopsa","words":["picaneábamos","picaneábamos"]},{"alpha":"aaaaglnpzi","words":["paganízala","paganízala","paganízala"]},{"alpha":"cceenooprr","words":["preconocer"]},{"alpha":"abehilmoprrsi","words":["prohibírmelas"]},{"alpha":"aaginooprrstza","words":["protagonizarás","protagonizarás"]},{"alpha":"eloprsto","words":["pórtelos"]},{"alpha":"aainpss","words":["pisanas","sapinas"]},{"alpha":"acefioprttuv","words":["putrefactivo"]},{"alpha":"aeeiilnoqrsu","words":["quinoleareis","quinoleareis"]},{"alpha":"biloorz","words":["roblizo"]},{"alpha":"bcdeilnooorstue","words":["robusteciéndolo"]},{"alpha":"ccceeinnoorrsstu","words":["reconstrucciones"]},{"alpha":"aacceioprt","words":["recapacito"]},{"alpha":"ceerstuo","words":["recuestó"]},{"alpha":"acdeerszu","words":["redúzcase"]},{"alpha":"aefillrru","words":["refluirla"]},{"alpha":"eefllmoorsste","words":["reflotémosles"]},{"alpha":"aeeelprri","words":["repelería"]},{"alpha":"eeirsstu","words":["rustiese","surtiese"]},{"alpha":"eeeemnorrsst","words":["reestrenemos"]},{"alpha":"aeeilorrste","words":["reitéraselo","reitéraselo"]},{"alpha":"egnoorz","words":["rezongo","rezongo"]},{"alpha":"bellnosuve","words":["sublévenlo"]},{"alpha":"aabcinnorsstu","words":["substanciaron"]},{"alpha":"afilsstue","words":["sulfatéis"]},{"alpha":"aalmrssa","words":["salmarás","salmarás"]},{"alpha":"eeeilmnnste","words":["siéntenmele"]},{"alpha":"egimorrssue","words":["surgiéremos"]},{"alpha":"ddeelnopsssue","words":["suspendédselo"]},{"alpha":"aeeefgilmorrsta","words":["telegrafiáremos"]},{"alpha":"elnnoste","words":["ténsenlo"]},{"alpha":"aabeeoqttu","words":["toqueteaba","toqueteaba"]},{"alpha":"aaimnoprrssstue","words":["transpusiéramos"]},{"alpha":"aaaalrrte","words":["tararéala","tararéala","tararéala"]},{"alpha":"aabclorrsti","words":["trascríbalo"]},{"alpha":"abddellnoorsta","words":["tresdoblándola"]},{"alpha":"aacehinorrsst","words":["trasnochareis","trasnochareis"]},{"alpha":"aaaersstz","words":["tarazases","tarazases"]},{"alpha":"aaiilmorsttuz","words":["titularizamos","titularizamos"]},{"alpha":"enttuo","words":["teutón"]},{"alpha":"cdeiimnova","words":["viciándome"]},{"alpha":"delouuv","words":["vueludo"]},{"alpha":"eeillnostve","words":["violénteles"]},{"alpha":"elmoy","words":["yelmo"]}]}