{"generated_on":1640276785466,"data":[{"alpha":"aaccdhnnoosa","words":["acachándonos"]},{"alpha":"aaaccesi","words":["acaecías"]},{"alpha":"aaccehlnoors","words":["acolchonares","acolchonares","acolchonares"]},{"alpha":"aaaclms","words":["aclamas","malcasa"]},{"alpha":"ceellnoossyu","words":["oclúyenosles"]},{"alpha":"aabcmoorrsstu","words":["acostumbraros"]},{"alpha":"aacdnoostuy","words":["acoyuntados"]},{"alpha":"aaacdeirsui","words":["adecuaríais","adecuaríais"]},{"alpha":"aabdeiilmosza","words":["idealizábamos","idealizábamos"]},{"alpha":"adefilmnora","words":["afirmándole"]},{"alpha":"aafilmmnoorse","words":["afirmémonosla"]},{"alpha":"aaaacflmorssa","words":["afascaláramos","afascaláramos"]},{"alpha":"aacdegirse","words":["agradecéis","desagracié"]},{"alpha":"aaaabdlors","words":["alabadoras"]},{"alpha":"aeegllsu","words":["allegues"]},{"alpha":"aceelqsu","words":["alqueces","alqueces"]},{"alpha":"aabceemsu","words":["embaucase","embaucase"]},{"alpha":"abelmmooqrsue","words":["embarquémoslo","embroquémosla"]},{"alpha":"bcdeeimnoorrta","words":["emborricándote"]},{"alpha":"abdeeglmnorsa","words":["embargándoles","embragándoles","gobernádmelas"]},{"alpha":"aeejmmopssa","words":["empajásemos","empajásemos"]},{"alpha":"aaaaeimrrssti","words":["amaestraríais","amaestraríais"]},{"alpha":"abceintu","words":["incúbate","incúbate","bauticen"]},{"alpha":"cceeeegnrua","words":["enceguecerá"]},{"alpha":"aacelmnnor","words":["encalmaron","encalmaron"]},{"alpha":"aabcdimnoo","words":["incomodaba"]},{"alpha":"aaceeilmnnrstte","words":["increméntatelas","increméntatelas"]},{"alpha":"adiins","words":["indias","nidias"]},{"alpha":"aadginnro","words":["andrógina"]},{"alpha":"addiiiinrsuve","words":["individuaréis"]},{"alpha":"aacefiinrst","words":["infectarais","infectarais","ratificasen","ratificasen","santificare","santificare","tarificasen","tarificasen"]},{"alpha":"adefiiinnrsu","words":["infundierais"]},{"alpha":"aaefiimnorsstz","words":["informatizases","informatizases"]},{"alpha":"ceeeghnnnsa","words":["engánchense"]},{"alpha":"eeeginrrs","words":["engrieres","reingrese"]},{"alpha":"aceeelmnnors","words":["enmalecernos","enmalecernos"]},{"alpha":"deinnou","words":["uniendo"]},{"alpha":"aacejlnorsze","words":["enrojézcalas"]},{"alpha":"abdellnnoota","words":["entablándolo"]},{"alpha":"aaabeelnrrt","words":["entablerara","entablerara","entablerara"]},{"alpha":"beeinnnosti","words":["entíbiennos"]},{"alpha":"aadeeeilnnrst","words":["entrelineadas"]},{"alpha":"aaaaenprrstzi","words":["entrapazarías","entrapazarías"]},{"alpha":"iinoqtuxe","words":["intoxiqué","intoxiqué"]},{"alpha":"aemoopsst","words":["apostemos"]},{"alpha":"aceeeloprs","words":["escopleare","escopleare"]},{"alpha":"aacpssuu","words":["usucapas"]},{"alpha":"aaefnorrsz","words":["esforzaran"]},{"alpha":"eilosn","words":["isleño"]},{"alpha":"aeegllpsuu","words":["espúlguela"]},{"alpha":"aeenorssso","words":["asesórenos"]},{"alpha":"abeeelmnstu","words":["estabúlenme"]},{"alpha":"adeiillnnoossstza","words":["estilizándonoslas"]},{"alpha":"aeeelmoqstue","words":["estoquéemela","estoquéamele","estoquéamele"]},{"alpha":"aeeeloprrssta","words":["estropeársela"]},{"alpha":"aaccefiiinrstto","words":["estratificación"]},{"alpha":"aafgiortuo","words":["autografió"]},{"alpha":"aaadloorstt","words":["atortoladas"]},{"alpha":"eeiost","words":["etesio"]},{"alpha":"aaeilnstve","words":["aviéntelas","aviéntales","aviéntales"]},{"alpha":"aaeelsttvi","words":["evítatelas","evítatelas"]},{"alpha":"admnoosuye","words":["ayudémonos"]},{"alpha":"abbeooss","words":["baboseos","baboseos"]},{"alpha":"abefisstu","words":["bufasteis","bufasteis"]},{"alpha":"abdeennoors","words":["bordoneasen","bordoneasen"]},{"alpha":"aaabmrrs","words":["bramaras","bramaras","bramaras","marrabas","marrabas"]},{"alpha":"aaabnrrrstu","words":["barruntaras","barruntaras","barruntaras"]},{"alpha":"aachlpu","words":["chalupa","chulapa","chúpala","chúpala","chúpala"]},{"alpha":"aaabcellrssi","words":["calíbraselas","calíbraselas"]},{"alpha":"aaceiilmsstz","words":["climatizases","climatizases"]},{"alpha":"acellnoore","words":["coloréenla"]},{"alpha":"aacillprrtua","words":["cultiparlará","cultiparlará"]},{"alpha":"cdeeellmmnnoopsta","words":["complementándoles"]},{"alpha":"accllmnnooosuya","words":["concluyámonosla"]},{"alpha":"cdeenrs","words":["cendres"]},{"alpha":"acgllmnooore","words":["congloméralo"]},{"alpha":"cdeilnnoost","words":["consentidlo"]},{"alpha":"aaceeinrrrstu","words":["canturreareis","canturreareis"]},{"alpha":"aaaabcnnorrti","words":["carbonatarían","carbonatarían"]},{"alpha":"aceeejrrs","words":["cerrajees","recejares","recejares","recejares","recejares"]},{"alpha":"acnorstu","words":["cúrtanos","truncaos","truncaos"]},{"alpha":"aaceilnorsstu","words":["cuestionarlas"]},{"alpha":"aceiiossttz","words":["cotizasteis","cotizasteis"]},{"alpha":"cdeeinos","words":["decenios"]},{"alpha":"aabcdeeeimnrst","words":["decrementabais"]},{"alpha":"adeegilnoqstui","words":["diagnostíquele"]},{"alpha":"adeeillste","words":["deléitelas","deléitales","deléitales"]},{"alpha":"aacddeimnoortz","words":["democratizando"]},{"alpha":"aaddmoors","words":["domadoras"]},{"alpha":"abdeeinrsz","words":["desbinzare","desbinzare"]},{"alpha":"abdeenrs","words":["desabren","desraben"]},{"alpha":"acddeelnooorsss","words":["desconsoladores","desconsoladores"]},{"alpha":"aaaacdeiilprsstz","words":["descapitalizaras","descapitalizaras","descapitalizaras"]},{"alpha":"aabcdeeimrrssu","words":["descerrumabais","descerrumabais"]},{"alpha":"acdiirrrssui","words":["discurrirías"]},{"alpha":"cdeeorsse","words":["descoseré"]},{"alpha":"adegimsstu","words":["disgústame"]},{"alpha":"dehinorsse","words":["deshonréis","deshornéis"]},{"alpha":"abddeellmnoossua","words":["desamueblándolos","desembaulándolos"]},{"alpha":"adddeejmnnoossa","words":["desmadejándonos"]},{"alpha":"adeeiilmmnnsyu","words":["disminúyanmele"]},{"alpha":"aadeenrssvi","words":["desnevarías","desvenarías","desvenarías"]},{"alpha":"adelopsz","words":["desplazo","desplazo"]},{"alpha":"adeeloprste","words":["despelotaré","despelotaré","torpedéelas","torpedéales","torpedéales"]},{"alpha":"adeeenpssz","words":["despezasen","despezasen"]},{"alpha":"aabdeeinpsz","words":["despiezaban"]},{"alpha":"addegoorst","words":["destorgado"]},{"alpha":"adeemstte","words":["destétame","detéstame"]},{"alpha":"addeilmnosvi","words":["divídanmelos"]},{"alpha":"aacdflnorsstua","words":["facturádnoslas"]},{"alpha":"afllos","words":["fallos","fallos","fallos","fallos","follas"]},{"alpha":"adfilnoor","words":["floridano"]},{"alpha":"aeefimnosstt","words":["fomentasteis"]},{"alpha":"aefgllnors","words":["frangolles","frangolles","frangolles"]},{"alpha":"eflnoorsa","words":["frenáoslo"]},{"alpha":"aabefgoorrt","words":["fotograbare","fotograbare"]},{"alpha":"aceefiiorsstv","words":["favorecisteis","vociferasteis","vociferasteis"]},{"alpha":"adeegllmnoossa","words":["glaseándomelos"]},{"alpha":"aaaegnrss","words":["gansearas","gansearas","gansearas"]},{"alpha":"aceginosstu","words":["gustaciones"]},{"alpha":"eehilnzo","words":["helenizó","helenizó"]},{"alpha":"aadehmnnr","words":["hermandan"]},{"alpha":"aaeeghinorssu","words":["hornagueaseis","hornagueaseis"]},{"alpha":"eefgiilnqsui","words":["lignifíquese","signifíquele"]},{"alpha":"ceefiilmnorsa","words":["lenificáremos","lenificáremos"]},{"alpha":"aaacdfiiilprsi","words":["lapidificarías","lapidificarías"]},{"alpha":"aillosvi","words":["llovíais"]},{"alpha":"aemmze","words":["mézame"]},{"alpha":"adeeilmorsz","words":["modelizares","modelizares","modelizares","modelizares"]},{"alpha":"aaabchimnrt","words":["marchitaban","marchitaban"]},{"alpha":"adllmmooru","words":["mormullado"]},{"alpha":"aimrrstu","words":["misturar"]},{"alpha":"acimrte","words":["métrica","térmica"]},{"alpha":"adelnprua","words":["pudelarán"]},{"alpha":"deilprrsu","words":["pudrirles","pudrirles"]},{"alpha":"aaeglpssa","words":["págaselas","págaselas"]},{"alpha":"aejlooprs","words":["pajoleros","pajoleros"]},{"alpha":"egillopsue","words":["pliéguelos"]},{"alpha":"aaennprtui","words":["puntearían","puntearían"]},{"alpha":"cddelmooprui","words":["producídmelo"]},{"alpha":"aefgilmoprrsue","words":["prefigurémosla"]},{"alpha":"aemnnoprsti","words":["permítannos"]},{"alpha":"noprto","words":["portón","protón"]},{"alpha":"eelmmnooqssue","words":["quemémonosles"]},{"alpha":"acdeeelmnorrsa","words":["recomendársela"]},{"alpha":"acceioprrrsa","words":["reciprocarás"]},{"alpha":"aadeijorrse","words":["rodajearéis","rodajearéis"]},{"alpha":"eeeeflmqrrsue","words":["refrésquemele"]},{"alpha":"eeghmoorrsa","words":["rehogáremos"]},{"alpha":"adehimnorrsui","words":["rehundiríamos"]},{"alpha":"aabellmmorsa","words":["remallábamos","remallábamos"]},{"alpha":"aeelnorsya","words":["reensáyalo"]},{"alpha":"adeelprt","words":["repletad","trepadle","trepadle"]},{"alpha":"bceeiorrs","words":["reescribo"]},{"alpha":"aeeprrrte","words":["retreparé","retreparé"]},{"alpha":"abeeerrrrve","words":["reverberaré","reverberaré"]},{"alpha":"cdeeeilnnoorrsva","words":["reverenciándolos"]},{"alpha":"abcirssstu","words":["subscritas"]},{"alpha":"aaelmorss","words":["salomares","salomares","salomares","salomares","salaremos","salaremos"]},{"alpha":"aabillmosszi","words":["simbolízalas","simbolízalas","simbolízalas"]},{"alpha":"aeilmnstue","words":["simultaneé","simultaneé"]},{"alpha":"eejlmmorsssua","words":["sumerjámosles"]},{"alpha":"inoorssse","words":["sonroséis"]},{"alpha":"aaeeiilmoprssttz","words":["temporalizasteis","temporalizasteis"]},{"alpha":"aeelnnstte","words":["tantéenles"]},{"alpha":"aaaanrrssstvi","words":["transvasarías","transvasarías"]},{"alpha":"ainoorstte","words":["tirotéanos","tirotéanos"]},{"alpha":"adeeiiilmnoprsv","words":["vilipendiaremos"]}]}