{"generated_on":1640276787092,"data":[{"alpha":"aabesst","words":["abastes","estabas","basaste","basaste","bastase","bastase","basteas","tesabas"]},{"alpha":"aabciorssttv","words":["abstractivos","abstractivos"]},{"alpha":"bdiorstu","words":["obstruid","disturbo","túrbidos","túrbidos"]},{"alpha":"acdejlmnnooopsa","words":["acomplejándonos"]},{"alpha":"aaaceenorsn","words":["acañoneares","acañoneares","acañoneares","acañoneares"]},{"alpha":"aaacegilmors","words":["acromegalias"]},{"alpha":"aaacelmtue","words":["acautélame"]},{"alpha":"adejlnostu","words":["adjúntelos"]},{"alpha":"aaeflmorti","words":["afírmatelo","afírmatelo"]},{"alpha":"aaaafgrrs","words":["agarrafas"]},{"alpha":"aeeegglnrsue","words":["agréguensele"]},{"alpha":"aadeglnoprssua","words":["agrupándoselas"]},{"alpha":"aaabciilrrsi","words":["albriciarías","calibraríais","calibraríais"]},{"alpha":"ceellmorssue","words":["ulcerémosles","esculléremos"]},{"alpha":"aaaacdlty","words":["alcayatad","alcayatad"]},{"alpha":"aaelmmorssa","words":["alarmásemos","alarmásemos","salmeáramos","salmeáramos"]},{"alpha":"aabceilmnori","words":["embolicarían","embolicarían"]},{"alpha":"aabdeemoqrtu","words":["embroquetada"]},{"alpha":"aadgimrue","words":["amadrigué","amadrigué"]},{"alpha":"aegiilmnorsta","words":["imaginártelos"]},{"alpha":"aellmmosue","words":["emulémosla"]},{"alpha":"aaeemnnsu","words":["amanuense"]},{"alpha":"aaeimnnorr","words":["aminoraren","marinearon","marinearon","reanimaron","reanimaron"]},{"alpha":"aeefilllmopro","words":["emperifóllalo"]},{"alpha":"aaabeegimmnpr","words":["empergaminaba","empergaminaba"]},{"alpha":"aaadmoprs","words":["amparados","pomaradas"]},{"alpha":"aaadellmorrt","words":["ametrallador"]},{"alpha":"accdeinosto","words":["anecdóticos","anecdóticos"]},{"alpha":"acceiilnrsu","words":["inculcareis","inculcareis"]},{"alpha":"ceeeilmnossa","words":["encielásemos"]},{"alpha":"aefiimnorrtuz","words":["uniformizarte"]},{"alpha":"aabefnrruun","words":["enfurruñaba","enfurruñaba"]},{"alpha":"ejlmnooosse","words":["enojémoslos"]},{"alpha":"aaeelmnrsi","words":["enmelarías","reanímelas","reanímales","reanímales"]},{"alpha":"abeeilnra","words":["enrábiela","enrábiale","enrábiale"]},{"alpha":"bciiinrssa","words":["inscribáis"]},{"alpha":"aacehnnss","words":["ensanchas"]},{"alpha":"aaadeeglnt","words":["entalegada"]},{"alpha":"aeeglnortte","words":["entrégatelo","entrégatelo"]},{"alpha":"aejnrtuo","words":["antruejó","antruejó"]},{"alpha":"aeeeiillnnrst","words":["interlineales"]},{"alpha":"aaeeinrstv","words":["antevieras","atraviesen","aventareis","ventearais","ventearais"]},{"alpha":"ddeeijnnoosva","words":["envedijándoos"]},{"alpha":"aeelpquo","words":["apóquele"]},{"alpha":"aaeirrte","words":["arietaré"]},{"alpha":"aeeinorttz","words":["erotizante","teorizante"]},{"alpha":"ceelmnooorssse","words":["esclerosémonos"]},{"alpha":"aaaabceeeijrssst","words":["escarabajeasteis","escarabajeasteis"]},{"alpha":"aabceersss","words":["escarbases","escarbases"]},{"alpha":"aeelmooss","words":["asoleemos"]},{"alpha":"aaelstta","words":["asáltate","asáltate","átatelas","átatelas"]},{"alpha":"aabeilnoprs","words":["espabilaron","espabilaron"]},{"alpha":"delnosua","words":["usándole"]},{"alpha":"abdeenost","words":["estebando"]},{"alpha":"aadeillmnopst","words":["estampillando","salpimentadlo","salpimentadlo"]},{"alpha":"aeelnrssti","words":["estríenlas","estírenlas","resístanle"]},{"alpha":"deelmnoorsstua","words":["esturándomelos","muestreándolos","muestreádnoslo"]},{"alpha":"aeeersttuy","words":["estatuyere"]},{"alpha":"adelnnooosstva","words":["estovándonosla"]},{"alpha":"dimnooosxe","words":["oxidémonos"]},{"alpha":"degiinosx","words":["exigidnos","exigidnos"]},{"alpha":"eelooprrssxa","words":["expresároslo"]},{"alpha":"aaabbdinorrz","words":["barbarizando"]},{"alpha":"abeejlnrsa","words":["barájenles","rebájenlas"]},{"alpha":"abelnnoqsssuu","words":["búsquennoslas"]},{"alpha":"bcemoorssa","words":["cobrásemos","cobrásemos"]},{"alpha":"cceehmoossa","words":["cocheásemos","cocheásemos"]},{"alpha":"accehhirro","words":["chicharreó","chicharreó"]},{"alpha":"acehmmoqssuu","words":["chamusquemos"]},{"alpha":"aaaabcehjnt","words":["chantajeaba","chantajeaba"]},{"alpha":"aaaccehiprsui","words":["chapucearíais","chapucearíais"]},{"alpha":"cceehlorsi","words":["choríceles"]},{"alpha":"acgllmnooosue","words":["colguémonosla"]},{"alpha":"abceflorso","words":["clerófobas"]},{"alpha":"aceeeiillqsssu","words":["cellisqueaseis","cellisqueaseis"]},{"alpha":"aabceilmmrsa","words":["cambiármelas"]},{"alpha":"bcceeiimnors","words":["coimbricense"]},{"alpha":"aabcdeimnop","words":["compendiaba"]},{"alpha":"accennorstu","words":["concursante"]},{"alpha":"acddina","words":["cándida"]},{"alpha":"cejnnnotu","words":["conjunten"]},{"alpha":"aacdiinorrsti","words":["contradiríais","doctrinaríais","doctrinaríais"]},{"alpha":"aclnoorrte","words":["controlaré"]},{"alpha":"acceellnorti","words":["centralícelo"]},{"alpha":"aceennnoorrt","words":["contornearen","contornearen"]},{"alpha":"aacdilmnoorsva","words":["convalidáramos","convalidáramos"]},{"alpha":"cilnoooprssa","words":["copiárnoslos"]},{"alpha":"acceemorrs","words":["cercaremos","cercaremos","recercamos","recercamos"]},{"alpha":"aaceimorrstuza","words":["cauterizáramos","cauterizáramos"]},{"alpha":"bdeeijlnosu","words":["dibújenselo","dibújenosle"]},{"alpha":"cdeelmoti","words":["díctemelo"]},{"alpha":"aadeeiilrst","words":["deleitarais","deleitarais"]},{"alpha":"aacdeilmnnsi","words":["dinamícenlas"]},{"alpha":"cddilooop","words":["diplodoco"]},{"alpha":"abcdeeimnrrs","words":["descimbraren","descimbraren"]},{"alpha":"aaddeiioorrssz","words":["desodorizarais","desodorizarais"]},{"alpha":"ddeeejlmnoorssa","words":["desmejorándoles"]},{"alpha":"adeiilmmnossyu","words":["disminúyamelos"]},{"alpha":"aadeemprrsva","words":["desemparvará","desemparvará"]},{"alpha":"acdeeillnops","words":["desencapillo"]},{"alpha":"deelnpssu","words":["despulsen"]},{"alpha":"aaddelpst","words":["desplatad","desplatad"]},{"alpha":"addeiprss","words":["dispersad","dispersad"]},{"alpha":"aaacdeehoprrsvi","words":["desaprovecharía","desaprovecharía"]},{"alpha":"aabdeorrssta","words":["desrabotarás","desrabotarás"]},{"alpha":"aabdeeeiilssstz","words":["desestabilizase","desestabilizase"]},{"alpha":"aadeeillnorssst","words":["desatornillases","desatornillases"]},{"alpha":"adeeeijrsv","words":["desviejare","desviejare"]},{"alpha":"aacdeemnossvz","words":["desvanezcamos"]},{"alpha":"adeegilsso","words":["desóigales"]},{"alpha":"aaadeinorssz","words":["desazonarais"]},{"alpha":"deeegiirsstt","words":["detergisteis"]},{"alpha":"acdefiiirrsve","words":["diversificaré","diversificaré"]},{"alpha":"abfilmnoooqrsue","words":["fabriquémonoslo"]},{"alpha":"acddefilnnoossuza","words":["fecundizándooslas"]},{"alpha":"efllmooste","words":["fletémoslo"]},{"alpha":"aadfins","words":["finadas"]},{"alpha":"aeefginosss","words":["fisgoneases","fisgoneases"]},{"alpha":"aadefilosssti","words":["fastídiaselos","fastídiaselos"]},{"alpha":"egllnoopse","words":["golpéenlos"]},{"alpha":"aabeginnost","words":["gestionaban"]},{"alpha":"cdehiiooprrsta","words":["hidroterápicos","hidroterápicos"]},{"alpha":"adghllmnooooa","words":["homologándola"]},{"alpha":"aaehmnrr","words":["hermanar"]},{"alpha":"aejlnoorrs","words":["jornaleros","jornaleros","sonrojarle"]},{"alpha":"aaaeijnqrrruzi","words":["jerarquizarían","jerarquizarían"]},{"alpha":"aacdefiiiilprs","words":["lapidificareis","lapidificareis"]},{"alpha":"deelnoy","words":["leyendo"]},{"alpha":"aallsve","words":["lévalas","lévalas","lévalas","vélalas","vélalas","vélalas"]},{"alpha":"eeillorv","words":["lloviere"]},{"alpha":"aagllmu","words":["magulla"]},{"alpha":"aceeimnnnos","words":["mencionasen"]},{"alpha":"abceiilprsu","words":["publicareis","publicareis"]},{"alpha":"aafiiprse","words":["piafaréis","piafaréis"]},{"alpha":"aegjoops","words":["pegajoso"]},{"alpha":"aaagprsi","words":["pagarías","pagarías"]},{"alpha":"aacdeilpsi","words":["palidecías"]},{"alpha":"aaabeeiilppstz","words":["papeletizabais","papeletizabais"]},{"alpha":"aemprri","words":["pírrame"]},{"alpha":"aelnooprrrste","words":["prorratéenlos"]},{"alpha":"adeegilnprs","words":["persignadle","persignadle"]},{"alpha":"adeelnoprstta","words":["prestándotela"]},{"alpha":"aaddiipsv","words":["pasividad"]},{"alpha":"aelmnqsue","words":["quémenlas"]},{"alpha":"aabbnoorr","words":["roboraban"]},{"alpha":"aacddeelru","words":["recaudadle","recaudadle","reeducadla","reeducadla"]},{"alpha":"abcdeeimmnora","words":["recambiándome"]},{"alpha":"aaacceinorrs","words":["reaccionaras","reaccionaras"]},{"alpha":"aaceillmoprsstue","words":["recapitulémoslas"]},{"alpha":"bdeellmoorse","words":["redoblémosle"]},{"alpha":"cddeeilnoorsue","words":["reduciéndoselo"]},{"alpha":"aeiillorrstuza","words":["reutilizárosla"]},{"alpha":"aacdeilnooruv","words":["revolucionada"]},{"alpha":"aaabnorsz","words":["razonabas"]},{"alpha":"aabcejlnorso","words":["sobrecójanla"]},{"alpha":"aabceinsssttu","words":["substanciaste"]},{"alpha":"aegrse","words":["segaré"]},{"alpha":"iilmoopsss","words":["solipsismo"]},{"alpha":"eellnossta","words":["sáltenselo","sáltenosle"]},{"alpha":"aeiinoorsssz","words":["sonorizaseis","sonorizaseis"]},{"alpha":"eenopprstu","words":["superponte","superponte"]},{"alpha":"eeeennrss","words":["serenense"]},{"alpha":"acehlnopsse","words":["sospéchenla"]},{"alpha":"aaadiilnqrtuz","words":["tranquilizada"]},{"alpha":"aadiiiprrstui","words":["tripudiaríais"]},{"alpha":"aaceeprrrssta","words":["trasparecerás"]},{"alpha":"aerrsstva","words":["trasverás"]},{"alpha":"aaamorsttui","words":["tatuaríamos"]},{"alpha":"aairrva","words":["variará"]}]}