{"generated_on":1640276786560,"data":[{"alpha":"bbilnoue","words":["obnubilé","obnubilé"]},{"alpha":"aabilloqru","words":["aboquillar","abarquillo"]},{"alpha":"acellloso","words":["acóllelos"]},{"alpha":"acellortui","words":["ocluírtela"]},{"alpha":"aaacellrse","words":["aceléralas","aceléralas","aceléralas"]},{"alpha":"acceinoto","words":["aconteció"]},{"alpha":"aacceeeimnnortt","words":["acrecentamiento"]},{"alpha":"aaccelorrsa","words":["acercárosla"]},{"alpha":"acdeilmorsue","words":["adulciéremos"]},{"alpha":"adinoors","words":["odiarnos","inodoras","orinados","sardonio"]},{"alpha":"aaadjmsu","words":["ajumadas"]},{"alpha":"aaabiilmnrsui","words":["albuminaríais","albuminaríais"]},{"alpha":"aadilns","words":["aldinas","alindas","ladinas","sandial"]},{"alpha":"abdeegmor","words":["embodegar","embregado"]},{"alpha":"aaadeimnnrs","words":["amadrinasen","amadrinasen","desimanaran","desimanaran","desanimaran","desanimaran"]},{"alpha":"aaceimns","words":["amencias","encamisa","caimanes","caminase","caminase"]},{"alpha":"aaaamnnnrza","words":["amanzanarán","amanzanarán"]},{"alpha":"aadeegmnptu","words":["empeguntada"]},{"alpha":"aelmmnoopr","words":["emplomaron","emplomaron"]},{"alpha":"aaillmprssu","words":["impulsarlas"]},{"alpha":"eeiimort","words":["omitiere"]},{"alpha":"aaabcellnnrui","words":["encabullarían","encabullarían"]},{"alpha":"aaceeejnrss","words":["encajerases","encajerases"]},{"alpha":"cdennoruo","words":["encornudó","encornudó"]},{"alpha":"abddelnoo","words":["endoblado"]},{"alpha":"adeeeiimnnors","words":["endemoniareis"]},{"alpha":"adefilnost","words":["enfistolad","infestadlo","infestadlo","finteadlos","finteadlos"]},{"alpha":"aaggiimnorrstui","words":["ingurgitaríamos","ingurgitaríamos"]},{"alpha":"aceellnoqsue","words":["enloquécelas","enloquécelas"]},{"alpha":"aaailnsst","words":["analistas"]},{"alpha":"aaabeillmnss","words":["enmasillabas","enmasillabas"]},{"alpha":"eelnoqsstui","words":["enquístelos","quítenselos","quítenosles"]},{"alpha":"aeehjmnoors","words":["enrehojamos","enrehojamos"]},{"alpha":"aeeegmnnrtti","words":["íntegramente"]},{"alpha":"aellnost","words":["entallos","entallos","entallos","entallos","tallones"]},{"alpha":"ceemnorte","words":["entrecomé","entrecomé"]},{"alpha":"adeeeimnrst","words":["entremedias","interesadme","interesadme","dementareis","demeritasen","demeritasen","desentarime","determinase","determinase","sedimentare"]},{"alpha":"aeeejlnnrstte","words":["entretéjanles"]},{"alpha":"eeellnsuvve","words":["envuélveles"]},{"alpha":"aaenpsstu","words":["apuntases","apuntases"]},{"alpha":"abilmoooprsse","words":["oprobiémoslas"]},{"alpha":"aaegiimnprsa","words":["apergamináis","apergamináis"]},{"alpha":"aeemoprrssu","words":["apresuremos","espurreamos","espurreamos","superaremos","superaremos"]},{"alpha":"acdeeiirrse","words":["arideceréis"]},{"alpha":"aaaegmnnrrtu","words":["argumentaran"]},{"alpha":"aadgrru","words":["arrugad","garruda","graduar","guardar"]},{"alpha":"aaelorun","words":["arañuelo"]},{"alpha":"aiilorrrt","words":["irritarlo"]},{"alpha":"acellmossu","words":["escullamos","escullamos","escullamos"]},{"alpha":"acdeeillnosvza","words":["esclavizándole"]},{"alpha":"aceemorrssza","words":["escarzáremos","escarzáremos"]},{"alpha":"aceefinoorrss","words":["esforrocinase","esforrocinase"]},{"alpha":"aellmossta","words":["esmáltalos","esmáltalos","esmáltalos","esmáltalos","sáltamelos","sáltamelos","tallásemos","tallásemos"]},{"alpha":"eeeflnsi","words":["esnífele","fíensele"]},{"alpha":"eeellopsse","words":["espoléeles"]},{"alpha":"adeelopssuz","words":["espeluzados","despeluzaos","despeluzaos"]},{"alpha":"aeelnprssi","words":["aspírenles"]},{"alpha":"eeelmoprrssue","words":["espurréemelos","espurreémosle"]},{"alpha":"eelorssste","words":["estréselos","résteselos"]},{"alpha":"adeeeeilnooprsttta","words":["estereotipándotela"]},{"alpha":"abeeeimooprsstta","words":["estereotipábamos","estereotipábamos"]},{"alpha":"eostve","words":["estové"]},{"alpha":"aadelnott","words":["atontadle","atontadle","tanteadlo","tanteadlo"]},{"alpha":"adeirrstu","words":["aturdirse","aturdirse","resurtida"]},{"alpha":"aaacdlnossta","words":["atascándolas"]},{"alpha":"aaeeiirssv","words":["averiaseis"]},{"alpha":"ceeeeelnpsstxu","words":["exceptúenseles"]},{"alpha":"eellostxa","words":["exáltelos"]},{"alpha":"aeeelmnnsxi","words":["examínenles"]},{"alpha":"aeeilmnoprtxe","words":["experiméntalo"]},{"alpha":"abbdei","words":["bebida"]},{"alpha":"aaabfgiiiorrs","words":["biografiarais"]},{"alpha":"abeejlor","words":["bajelero"]},{"alpha":"bcddeiilnnoose","words":["bendiciéndolos"]},{"alpha":"abeenqu","words":["baqueen"]},{"alpha":"aabeijlrrs","words":["barrilajes"]},{"alpha":"aabeelrstz","words":["brazaletes"]},{"alpha":"bccehioz","words":["bizcoche"]},{"alpha":"aabceeillrse","words":["caballereéis"]},{"alpha":"aaabcillsst","words":["caballistas"]},{"alpha":"aabccdehmnoosa","words":["cachondeábamos","cachondeábamos"]},{"alpha":"aaaccdilnrruui","words":["cuadricularían","cuadricularían"]},{"alpha":"aaclmors","words":["calmaros","colmaras","colmaras","colmaras","lacramos","lacramos","morlacas"]},{"alpha":"aclorrru","words":["clorurar"]},{"alpha":"ciimmoprrsa","words":["comprimirás"]},{"alpha":"aaccceiinnnori","words":["concienciarían"]},{"alpha":"aacceinorrstz","words":["concretizaras","concretizaras","concretizaras"]},{"alpha":"cdefinnorsu","words":["confundirse","confundirse"]},{"alpha":"accgijnnouo","words":["conjugación"]},{"alpha":"acilmnoosan","words":["ciñámonosla"]},{"alpha":"acceinnnoost","words":["consonantice"]},{"alpha":"celnooorrsssva","words":["conservároslos"]},{"alpha":"acdilnnnooosstua","words":["contusionándolas","contusionádnosla"]},{"alpha":"aaaabceinnpt","words":["capitaneaban","capitaneaban"]},{"alpha":"ceejmoost","words":["cotejemos"]},{"alpha":"aaacegllnosstuo","words":["catalóguenoslas"]},{"alpha":"aabdddillloo","words":["dobladillado"]},{"alpha":"addeimnnoo","words":["denominado"]},{"alpha":"aadeellnnrt","words":["dentellaran","dentellaran"]},{"alpha":"acddeillnopstua","words":["duplicándotelas"]},{"alpha":"aacddehoorrrs","words":["derrochadoras"]},{"alpha":"cddeeiimorsse","words":["descomediréis"]},{"alpha":"accdeemnooorssi","words":["desconoceríamos"]},{"alpha":"cddeeeeinrss","words":["descendieres"]},{"alpha":"aacdeeilnrrstza","words":["descentralizará","descentralizará"]},{"alpha":"aabcdeelrrse","words":["descerébrala","descerébrala","descerébrala"]},{"alpha":"aaaddeimrrsstza","words":["desdramatizarás","desdramatizarás"]},{"alpha":"adeefgors","words":["desfogare"]},{"alpha":"addeglnnooorrssa","words":["desgarrándonoslo"]},{"alpha":"bdeehirsse","words":["deshebréis","desherbéis"]},{"alpha":"adeehlnsssue","words":["deshuésenlas"]},{"alpha":"aaddeeiilmnorss","words":["desalmidonareis"]},{"alpha":"deeeglmnossu","words":["deslengüemos"]},{"alpha":"addeeejmmorssa","words":["desmadejáremos","desmadejáremos"]},{"alpha":"aaaddemrrss","words":["desmadraras","desmadraras","desmadraras"]},{"alpha":"ddeiiilmnssu","words":["disminuidles"]},{"alpha":"aaddeefinrsse","words":["desenfadaréis","desenfadaréis"]},{"alpha":"adeennnorsta","words":["desentonarán"]},{"alpha":"aaadeemnpprss","words":["despampanares","despampanares","despampanares","despampanares"]},{"alpha":"adiiiopssstv","words":["dispositivas"]},{"alpha":"ddeeioqrssu","words":["desqueridos"]},{"alpha":"aabdeinprst","words":["destripaban","destripaban"]},{"alpha":"ddeiisttu","words":["destituid"]},{"alpha":"addeenrti","words":["detendría"]},{"alpha":"acdefhnoos","words":["fachendoso"]},{"alpha":"aaceefhss","words":["facheases","facheases"]},{"alpha":"afgimorsu","words":["figuramos","figuramos","fumigaros"]},{"alpha":"eflllnoue","words":["fuéllenlo"]},{"alpha":"aaflllmosse","words":["fallémoslas"]},{"alpha":"abeeflmoorsta","words":["floreteábamos","floreteábamos"]},{"alpha":"addfnnosu","words":["fundadnos","fundadnos"]},{"alpha":"aefjlorsso","words":["fórjaselos","fórjaselos"]},{"alpha":"adfilnostu","words":["fistulando"]},{"alpha":"aceeegrrtu","words":["guarecerte","guarecerte"]},{"alpha":"aaaabcdgrrsu","words":["guardacabras"]},{"alpha":"acefgiilorsssa","words":["gasificárselos"]},{"alpha":"aaglnosssta","words":["gástanoslas"]},{"alpha":"ahmor","words":["horma"]},{"alpha":"aaeegilmnrs","words":["lagrimeasen","lagrimeasen","milagreasen","milagreasen"]},{"alpha":"ellnoi","words":["líenlo"]},{"alpha":"aaiiilmprs","words":["limpiarais"]},{"alpha":"cegilorsta","words":["letárgicos","letárgicos"]},{"alpha":"aademrra","words":["madreará","madreará"]},{"alpha":"aacdfgiilmnnoa","words":["magnificándola"]},{"alpha":"diilmu","words":["mildiu"]},{"alpha":"addeeellmnnost","words":["malentendedlos","malentendedlos"]},{"alpha":"adeegimmnnossua","words":["mindangueásemos","mindangueásemos"]},{"alpha":"aamrno","words":["marañó","marañó"]},{"alpha":"acceimorssta","words":["mesocráticas"]},{"alpha":"imosz","words":["mizos","mizos"]},{"alpha":"aailnnoopt","words":["napolitano"]},{"alpha":"alnosto","words":["nótalos","nótalos","nótalos","nótalos"]},{"alpha":"aaceeinps","words":["picanease","picanease"]},{"alpha":"cdilnoopssa","words":["picádnoslos"]},{"alpha":"aaaegilnps","words":["pelagianas"]},{"alpha":"ellmoopsse","words":["pelémoslos","soplémosle"]},{"alpha":"eillopse","words":["polleéis"]},{"alpha":"acdeeinnpr","words":["pendenciar"]},{"alpha":"einopp","words":["pepino"]},{"alpha":"eeeflmprsu","words":["perfúmeles"]},{"alpha":"adeilmoprrsua","words":["preludiáramos"]},{"alpha":"aceeopprrrse","words":["preprocesaré"]},{"alpha":"adeeinoprrsu","words":["persuadieron"]},{"alpha":"aaloprsve","words":["provéalas"]},{"alpha":"aacpsu","words":["pascua"]},{"alpha":"aceiilnoopssto","words":["posiciónatelos","posiciónatelos"]},{"alpha":"aaellprsttu","words":["patrullaste","patrullaste"]},{"alpha":"ainoqrtu","words":["quitaron","quitaron"]},{"alpha":"abelnoorr","words":["roblonare"]},{"alpha":"ceiinorrstva","words":["reconvirtáis"]},{"alpha":"definrru","words":["refundir"]},{"alpha":"abehiiilrsta","words":["rehabilitáis","rehabilitáis"]},{"alpha":"eejlro","words":["relejó","relejó"]},{"alpha":"aeilrsza","words":["realzáis","realzáis","relazáis","relazáis"]},{"alpha":"deeelmrse","words":["remédeles"]},{"alpha":"eeegilnrrte","words":["reintégrele"]},{"alpha":"eeeiipqrstue","words":["repiqueteéis"]},{"alpha":"aaaahillprrss","words":["raspahilarlas"]},{"alpha":"abbbeenorsi","words":["sobrebebían","sobrebebían"]},{"alpha":"aabdeegmorsu","words":["sobreaguadme","sobreaguadme"]},{"alpha":"beeelllnorsve","words":["sobrellévenle"]},{"alpha":"bdelnnooorsa","words":["sobornándole"]},{"alpha":"begiinorssuu","words":["subsiguieron"]},{"alpha":"aaaddiillorsz","words":["solidarizadla","solidarizadla"]},{"alpha":"delllnoossa","words":["sellándolos"]},{"alpha":"deeimnnqsui","words":["sindíquenme"]},{"alpha":"aabdennprsuu","words":["superabundan"]},{"alpha":"abcelnnorsssui","words":["suscríbannosle"]},{"alpha":"acelnsstui","words":["suscítenla"]},{"alpha":"acdhiosssu","words":["susodichas"]},{"alpha":"afgimorsso","words":["sismógrafo"]},{"alpha":"aaiiilrsstuzi","words":["sutilizaríais","sutilizaríais"]},{"alpha":"abeinqtu","words":["tabiquen"]},{"alpha":"aaellmoopprsste","words":["traspapelémoslo"]},{"alpha":"aadeeorrsstt","words":["trasteadores","trasteadores"]},{"alpha":"aaaillrsttuzi","words":["titularízalas","titularízalas","titularízalas"]},{"alpha":"aaaelrtte","words":["tataréela","tataréale","tataréale"]},{"alpha":"cdeorsuv","words":["verdusco"]},{"alpha":"aaeeqrrrsuv","words":["verraqueras"]},{"alpha":"abdeelnorrtva","words":["vertebrándola"]},{"alpha":"eeemostv","words":["veteemos"]},{"alpha":"aelnooprstuxy","words":["yuxtaponerlos","yuxtaponerlos"]}]}